jiralogin/JiraLogin.py
JiraLogin-1.0.4.dist-info/LICENSE.txt
JiraLogin-1.0.4.dist-info/METADATA
JiraLogin-1.0.4.dist-info/WHEEL
JiraLogin-1.0.4.dist-info/top_level.txt
JiraLogin-1.0.4.dist-info/RECORD
