Metadata-Version: 2.1
Name: JiraLogin
Version: 1.0.4
Summary: A Jira login assistant that saves credentials for individual servers locally for future use.
Home-page: UNKNOWN
Author: Mason Hanson
Author-email: UNKNOWN
License: MIT License
Keywords: jira atlassian authentication
Platform: UNKNOWN
Requires-Dist: Jira (>=2.0.0)
